{
    "name": "Employee",
    "fields": [
        {
            "fieldName": "umane",
            "javadoc": "The firstname attribute.",
            "fieldType": "String",
            "fieldValidateRules": [
                "required"
            ]
        },
        {
            "fieldName": "firstName",
            "fieldType": "String"
        },
        {
            "fieldName": "lastName",
            "fieldType": "String"
        },
        {
            "fieldName": "email",
            "fieldType": "String",
            "fieldValidateRules": [
                "required"
            ]
        },
        {
            "fieldName": "phoneNumber",
            "fieldType": "String"
        },
        {
            "fieldName": "hireDate",
            "fieldType": "Instant"
        }
    ],
    "relationships": [
        {
            "relationshipType": "one-to-many",
            "otherEntityName": "briefing",
            "otherEntityRelationshipName": "employee",
            "relationshipName": "briefing"
        },
        {
            "relationshipType": "one-to-many",
            "otherEntityName": "employee",
            "otherEntityRelationshipName": "employee",
            "relationshipName": "manager"
        },
        {
            "relationshipType": "many-to-one",
            "otherEntityName": "employee",
            "otherEntityRelationshipName": "manager",
            "relationshipName": "employee",
            "otherEntityField": "id"
        },
        {
            "relationshipType": "many-to-many",
            "otherEntityName": "department",
            "otherEntityRelationshipName": "employee",
            "javadoc": "Another side of the same relationship",
            "relationshipName": "department",
            "otherEntityField": "id",
            "ownerSide": false
        }
    ],
    "changelogDate": "20191227130315",
    "javadoc": "The Employee entity.",
    "entityTableName": "employee",
    "dto": "no",
    "pagination": "infinite-scroll",
    "service": "no",
    "jpaMetamodelFiltering": false,
    "fluentMethods": true,
    "readOnly": false,
    "clientRootFolder": "",
    "applications": "*"
}